json5/__init__.py
json5/dumper.py
json5/loader.py
json5/model.py
json5/parser.py
json5/py.typed
json5/tokenizer.py
json5/utils.py
json_five-1.1.2.dist-info/LICENSE
json_five-1.1.2.dist-info/METADATA
json_five-1.1.2.dist-info/WHEEL
json_five-1.1.2.dist-info/top_level.txt
json_five-1.1.2.dist-info/RECORD
