Metadata-Version: 2.1
Name: json-five
Version: 1.1.2
Summary: A JSON5 parser that, among other features, supports round-trip preservation of comments
Home-page: https://github.com/spyoungtech/json-five
Author: Spencer Phillip Young
Author-email: spencer.young@spyoung.com
License: Apache
Classifier: License :: OSI Approved :: Apache Software License
Classifier: Programming Language :: Python :: 3 :: Only
Classifier: Programming Language :: Python :: 3.8
Classifier: Programming Language :: Python :: 3.9
Classifier: Programming Language :: Python :: 3.10
Classifier: Programming Language :: Python :: 3.11
Requires-Python: >=3.8.0
License-File: LICENSE
Requires-Dist: sly>=0.5
Requires-Dist: regex
